orchestcli/__init__.py
orchestcli/_version.py
orchestcli/cli.py
orchestcli/cmds.py
orchestcli/utils.py
tto_cli-0.8.2.dist-info/LICENSE
tto_cli-0.8.2.dist-info/METADATA
tto_cli-0.8.2.dist-info/WHEEL
tto_cli-0.8.2.dist-info/entry_points.txt
tto_cli-0.8.2.dist-info/top_level.txt
tto_cli-0.8.2.dist-info/RECORD
